CHANGELOG.txt
LICENSE.txt
MANIFEST.in
README.txt
__init__.py
click.py
setup.py
pythonclicker27.egg-info/PKG-INFO
pythonclicker27.egg-info/SOURCES.txt
pythonclicker27.egg-info/dependency_links.txt
pythonclicker27.egg-info/requires.txt
pythonclicker27.egg-info/top_level.txt