Metadata-Version: 2.1
Name: pythonclicker27
Version: 0.0.5
Summary: A simple and easy-to-use autoclicker library for Python
Home-page: https://github.com/FJ27cool/PyClicker27
Author: FJ27cool
License: MIT
Keywords: autoclicker,python,clicker,automation,pyclicker27
Classifier: Development Status :: 5 - Production/Stable
Classifier: Development Status :: 4 - Beta
Classifier: Development Status :: 3 - Alpha
Classifier: Programming Language :: Python
Classifier: Programming Language :: Python :: 3
Classifier: Programming Language :: Python :: 3.6
Classifier: Programming Language :: Python :: 3.7
Classifier: Programming Language :: Python :: 3.8
Classifier: Programming Language :: Python :: 3.9
Classifier: Programming Language :: Python :: 3.10
Classifier: Programming Language :: Python :: 3.11
Classifier: Programming Language :: Python :: 3.12
Classifier: Programming Language :: Python :: 3.13
Classifier: License :: OSI Approved :: MIT License
Classifier: Operating System :: Microsoft :: Windows
Classifier: Intended Audience :: Developers
Classifier: Intended Audience :: End Users/Desktop
Classifier: Natural Language :: English
Classifier: Topic :: Software Development :: Libraries :: Python Modules
Classifier: Topic :: Utilities
Classifier: Environment :: Console
Classifier: Environment :: Win32 (MS Windows)
Requires-Python: >=3.6
License-File: LICENSE.txt
